LICENSE
MANIFEST.in
README.md
requirements.txt
setup.py
torch_lr_scheduler/__init__.py
torch_lr_scheduler/__version__.py
torch_lr_scheduler/lr_scheduler.py
torch_lr_scheduler.egg-info/PKG-INFO
torch_lr_scheduler.egg-info/SOURCES.txt
torch_lr_scheduler.egg-info/dependency_links.txt
torch_lr_scheduler.egg-info/requires.txt
torch_lr_scheduler.egg-info/top_level.txt
torch_lr_scheduler/configs/__init__.py
torch_lr_scheduler/configs/build/__init__.py
torch_lr_scheduler/configs/build/lr_scheduler_config.py
torch_lr_scheduler/schema/lr_scheduler_config.json