Metadata-Version: 2.1
Name: torch-lr-scheduler
Version: 0.0.5.post4
Summary: PyTorch Optimizer Lr Scheduler
Home-page: https://github.com/FebruaryBreeze/torch-lr-scheduler
Author: SF-Zhou
Author-email: sfzhou.scut@gmail.com
License: MIT
Keywords: PyTorch Lr Scheduler
Platform: UNKNOWN
Requires-Python: >=3.6.0
